secugenpy/__init__.py
secugenpy/secugen.py
secugenpy-1.0.1.dist-info/METADATA
secugenpy-1.0.1.dist-info/WHEEL
secugenpy-1.0.1.dist-info/top_level.txt
secugenpy-1.0.1.dist-info/RECORD
