Metadata-Version: 2.4
Name: secugenpy
Version: 1.0.1
Summary: Secugenpy est un module Python conçu pour la capture et la comparaison d'empreintes digitales à l'aide des lecteurs biométriques SecuGen.
Author: MAZIKOU Franck Souverain
Author-email: franckmazikous@gmail.com
Classifier: Programming Language :: Python :: 3
Classifier: Operating System :: Microsoft :: Windows
Requires-Python: >=3.10
Requires-Dist: Pillow>=9.0.0
Dynamic: author
Dynamic: author-email
Dynamic: classifier
Dynamic: description
Dynamic: description-content-type
Dynamic: requires-dist
Dynamic: requires-python
Dynamic: summary
